Workbook

Sheet Presupuesto
A1: Presupuesto del Proyecto de Reingeniería (MXN)
A2: Costo por persona-mes tomado de la Práctica 5. Azul = dato editable; verde = viene de otra hoja.
A4: Fase / Milestone | B4: % del esfuerzo | C4: Personas-mes | D4: Costo (MXN)
A5: Fase 1. Inicio y análisis | B5: 0.08 | C5: =B5*Esfuerzo!$B$15 -> 1.5014856 | D5: =C5*'Base P5'!$B$14 -> 28152.855
A6: Fase 2. Diseño y arquitectura | B6: 0.12 | C6: =B6*Esfuerzo!$B$15 -> 2.2522284 | D6: =C6*'Base P5'!$B$14 -> 42229.283
A7: Fase 3. Base de datos y protección de datos | B7: 0.22 | C7: =B7*Esfuerzo!$B$15 -> 4.1290854 | D7: =C7*'Base P5'!$B$14 -> 77420.352
A8: Fase 4. Migración de módulos al framework actual | B8: 0.35 | C8: =B8*Esfuerzo!$B$15 -> 6.5689995 | D8: =C8*'Base P5'!$B$14 -> 123168.74
A9: Fase 5. Pruebas y aseguramiento de calidad | B9: 0.15 | C9: =B9*Esfuerzo!$B$15 -> 2.8152855 | D9: =C9*'Base P5'!$B$14 -> 52786.603
A10: Fase 6. Despliegue, capacitación y cierre | B10: 0.08 | C10: =B10*Esfuerzo!$B$15 -> 1.5014856 | D10: =C10*'Base P5'!$B$14 -> 28152.855
A11: Subtotal de personal | B11: =SUM(B5:B10) -> 1 | C11: =SUM(C5:C10) -> 18.76857 | D11: =SUM(D5:D10) -> 351910.69
A13: Otros costos directos | B13: Cantidad | C13: Costo unitario (MXN) | D13: Costo (MXN)
A14: Infraestructura y hosting, pruebas y producción (meses) | B14: 6 | C14: 4000 | D14: =B14*C14 -> 24000
A15: Licencias y herramientas: dominio, certificado SSL, respaldos (paquete) | B15: 1 | C15: 8000 | D15: =B15*C15 -> 8000
A16: Capacitación a usuarios y administradores (paquete) | B16: 1 | C16: 15000 | D16: =B16*C16 -> 15000
A17: Asesoría jurídica: aviso de privacidad y licencia del repositorio (paquete) | B17: 1 | C17: 15000 | D17: =B17*C17 -> 15000
A18: Subtotal otros costos | B18: — | C18: — | D18: =SUM(D14:D17) -> 62000
A20: Resumen | B20: Porcentaje | C20: Base de cálculo (MXN) | D20: Monto (MXN)
A21: Costo directo total (personal + otros) | B21: 1 | C21: =D11+D18 -> 413910.69 | D21: =B21*C21 -> 413910.69
A22: Reserva para contingencias (sobre costo directo) | B22: =Contingencia!C19 -> 0.2 | C22: =D21 -> 413910.69 | D22: =B22*C22 -> 82782.138
A23: Total antes de IVA | B23: 1 | C23: =D21+D22 -> 496692.83 | D23: =B23*C23 -> 496692.83
A24: IVA | B24: 0.16 | C24: =D23 -> 496692.83 | D24: =B24*C24 -> 79470.852
A25: PRECIO TOTAL DE LA PROPUESTA | B25: 1 | C25: =D23+D24 -> 576163.68 | D25: =B25*C25 -> 576163.68
A27: Duración | B27: Valor | C27: Unidad | D27: Fuente
A28: Integrantes de la consultora | B28: 6 | C28: personas | D28: Práctica 8: consultora de 6 integrantes
A29: Duración estimada del proyecto | B29: =C11/B28 -> 3.128095 | C29: meses | D29: Personas-mes ÷ integrantes
A30: Tiempo COCOMO de la Práctica 5 | B30: ='Base P5'!B7 -> 9.0896936 | C30: meses | D30: Práctica 5 (referencia)
A31: Duración real del desarrollo original | B31: =86/30.4 -> 2.8289474 | C31: meses | D31: historial.txt: 86 días entre commits
A33: Nota: los otros costos directos son SUPUESTOS; no vienen de la Práctica 5.

Sheet Base P5
A1: Base de Estimación (Práctica 5)
A2: Datos tomados de estimacion.xlsx y estimacion.md. Azul = dato de entrada; negro = fórmula.
A4: Concepto | B4: Valor | C4: Fuente / nota
A5: KLOC de código propio | B5: 11.039 | C5: Práctica 5, conteo LOC (11,039 líneas)
A6: Esfuerzo COCOMO orgánico (personas-mes) | B6: =2.4*B5^1.05 -> 29.873593 | C6: E = 2.4 × KLOC^1.05
A7: Tiempo COCOMO (meses) | B7: =2.5*B6^0.38 -> 9.0896936 | C7: T = 2.5 × E^0.38
A8: Puntos de función sin ajustar | B8: 249 | C8: Práctica 5, complejidad media
A9: Productividad (horas/PF) | B9: 7 | C9: Práctica 5 (Capers Jones / SPR / ISBSG, PHP)
A10: Horas-persona por mes | B10: 160 | C10: Práctica 5
A11: Esfuerzo Puntos de Función (personas-mes) | B11: =B8*B9/B10 -> 10.89375 | C11: 249 PF × 7 h / 160 h
A12: Salario mensual desarrollador junior (MXN) | B12: 15000 | C12: Práctica 5 (Indeed / OCC, San Luis Potosí)
A13: Costos indirectos | B13: 0.25 | C13: Práctica 5
A14: Costo mensual cargado por persona (MXN) | B14: =B12*(1+B13) -> 18750 | C14: Práctica 5: $18,750/mes
A15: Costo estimado COCOMO (MXN) | B15: =B6*B14 -> 560129.87 | C15: Práctica 5
A16: Costo estimado Puntos de Función (MXN) | B16: =B11*B14 -> 204257.81 | C16: Práctica 5
A17: Esfuerzo de consenso (personas-mes) | B17: =AVERAGE(B6,B11) -> 20.383672 | C17: SUPUESTO: la Ronda Delphi quedó pendiente (delphi.md); se usa el promedio de ambos métodos. Sustituir por la cifra de consenso cuando la tengas.

Sheet Esfuerzo
A1: Esfuerzo Ajustado Al Nuevo Alcance
A2: Del esfuerzo de consenso de la Práctica 5 al esfuerzo del proyecto de reingeniería.
A4: Concepto | B4: Personas-mes | C4: Nota
A5: Esfuerzo de consenso (Práctica 5) | B5: ='Base P5'!B17 -> 20.383672 | C5: Vinculado a la hoja Base P5
A6: Factor de reutilización | B6: 0.7 | C6: SUPUESTO: se conserva la lógica de negocio y las 17 tablas; se reescribe la capa técnica
A7: Esfuerzo base ajustado | B7: =B5*B6 -> 14.26857 | C7: Migración a framework actual
A9: Trabajo adicional del nuevo alcance | B9: Personas-mes | C9: Hallazgo que atiende
A10: Protección de datos y seguridad (hash de contraseñas, secretos fuera del código, retiro de datos personales del repositorio, aviso de privacidad y derechos ARCO) | B10: 2 | C10: Top 10 de riesgos: #1, #2, #3, #4 y #8
A11: Rediseño de base de datos (llaves foráneas, normalizar solicitudes, unificar referencia a usuario, tipos de dato, script único versionado) | B11: 1.5 | C11: evaluacion-modelo.md y Top 10 #7
A12: Pruebas automáticas y documentación técnica (README, manual de instalación) | B12: 1 | C12: Top 10 #5 y #10
A13: Subtotal trabajo adicional | B13: =SUM(B10:B12) -> 4.5 | C13: Suma de los tres conceptos
A15: ESFUERZO TOTAL DEL PROYECTO | B15: =B7+B13 -> 18.76857 | C15: Base ajustada + trabajo adicional

Sheet Contingencia
A1: Reserva Para Contingencias Sustentada En El Top 10 (Práctica 7)
A2: La reserva crece con la exposición promedio de los riesgos acordados el 28 de septiembre de 2026.
A4: # | B4: Riesgo | C4: Exposición
A5: 1 | B5: Documentos personales y respaldos .sql en el repositorio | C5: 25
A6: 2 | B6: Credenciales y claves en el código | C6: 25
A7: 3 | B7: Contraseñas en texto plano | C7: 25
A8: 4 | B8: Sin aviso de privacidad ni protección de datos | C8: 20
A9: 5 | B9: Un solo desarrollador, sin mantenimiento desde 2021 | C9: 20
A10: 6 | B10: PHP 7.2.34 fuera de soporte | C10: 20
A11: 7 | B11: Script de BD incompleto y tres versiones de respaldo | C11: 20
A12: 8 | B12: Conexión a la BD con root sin contraseña | C12: 16
A13: 9 | B13: Repositorio sin licencia | C13: 16
A14: 10 | B14: Sin pruebas automáticas | C14: 15
B16: Exposición promedio | C16: =AVERAGE(C5:C14) -> 20.2
B17: Exposición máxima de la escala (5 × 5) | C17: 25
B18: Contingencia máxima (con exposición máxima) | C18: 0.25
B19: % de contingencia aplicado | C19: =ROUND(C16/C17*C18,2) -> 0.2
B21: SUPUESTO: el 25% máximo es un criterio propio (el rango habitual de reserva es 10-25%). Ajusta C18 si tu docente pide otro.
